elliptic_sdk/__init__.py
elliptic_sdk/aml.py
elliptic_sdk/auth.py
elliptic_sdk/client.py
elliptic_sdk/enums.py
elliptic_sdk/schemas.py
elliptic_sdk/settings.py
elliptic_sdk-0.0.6.dist-info/LICENSE
elliptic_sdk-0.0.6.dist-info/METADATA
elliptic_sdk-0.0.6.dist-info/WHEEL
elliptic_sdk-0.0.6.dist-info/RECORD
