Metadata-Version: 2.1
Name: elliptic-sdk
Version: 0.0.6
Summary: Elliptic SDK
Author: Olexandr Shalakhin
Author-email: olexandr@shalakhin.com
Requires-Python: >=3.10,<4.0
Classifier: Programming Language :: Python :: 3
Classifier: Programming Language :: Python :: 3.10
Classifier: Programming Language :: Python :: 3.11
Requires-Dist: httpx (>=0.24.0,<0.25.0)
Requires-Dist: pydantic (>=1.10.7,<2.0.0)
Requires-Dist: python-dotenv (>=1.0.0,<2.0.0)
